mkdocs_table_of_figures/__init__.py
mkdocs_table_of_figures/builder.py
mkdocs_table_of_figures/config.py
mkdocs_table_of_figures/constants.py
mkdocs_table_of_figures/plugin.py
mkdocs_table_of_figures/assets/__init__.py
mkdocs_table_of_figures/assets/stylesheets/__init__.py
mkdocs_table_of_figures/assets/stylesheets/figures/__init__.py
mkdocs_table_of_figures/assets/stylesheets/figures/codeblock.css
mkdocs_table_of_figures/assets/stylesheets/figures/mermaid.css
mkdocs_table_of_figures/assets/stylesheets/figures/pair.css
mkdocs_table_of_figures/structure/__init__.py
mkdocs_table_of_figures/structure/collection.py
mkdocs_table_of_figures/structure/directive.py
mkdocs_table_of_figures/structure/figure.py
mkdocs_table_of_figures/structure/figure_type/__init__.py
mkdocs_table_of_figures/structure/figure_type/builtin_configs/__init__.py
mkdocs_table_of_figures/structure/figure_type/builtin_configs/codeblock.yml
mkdocs_table_of_figures/structure/figure_type/builtin_configs/image.yml
mkdocs_table_of_figures/structure/figure_type/builtin_configs/mermaid.yml
mkdocs_table_of_figures/structure/figure_type/builtin_configs/pair.yml
mkdocs_table_of_figures/structure/figure_type/builtin_configs/table.yml
mkdocs_table_of_figures/templates/__init__.py
mkdocs_table_of_figures/templates/output.md.j2
mkdocs_table_of_figures/translations/__init__.py
mkdocs_table_of_figures/translations/de.json
mkdocs_table_of_figures/translations/en.json
mkdocs_table_of_figures/translations/fr.json
mkdocs_table_of_figures-0.5.7.dist-info/METADATA
mkdocs_table_of_figures-0.5.7.dist-info/WHEEL
mkdocs_table_of_figures-0.5.7.dist-info/entry_points.txt
mkdocs_table_of_figures-0.5.7.dist-info/top_level.txt
mkdocs_table_of_figures-0.5.7.dist-info/RECORD
