Metadata-Version: 2.4
Name: mkdocs-table-of-figures
Version: 0.5.7
Summary: A MkDocs plugin listing all figures to create a table of figures
Home-page: https://gitlab.com/thiti-mkdocs-plugins/mkdocs-table-of-figures
Author: Thibaud Briard
Author-email: thibaud.briard@outlook.com
License: MIT
Keywords: mkdocs
Classifier: Development Status :: 3 - Alpha
Classifier: Intended Audience :: Developers
Classifier: Intended Audience :: Education
Classifier: Programming Language :: Python
Classifier: Programming Language :: Python :: 3 :: Only
Requires-Python: >=3.8
Requires-Dist: mkdocs>=1.6.0
Requires-Dist: Jinja2>=3.1.6
